vistopics/__init__.py
vistopics/captioning.py
vistopics/extract_frames.py
vistopics/image_download.py
vistopics/reduce_frame.py
vistopics/video_scrape.py
vistopics-0.1.8.dist-info/licenses/LICENSE
vistopics-0.1.8.dist-info/METADATA
vistopics-0.1.8.dist-info/WHEEL
vistopics-0.1.8.dist-info/top_level.txt
vistopics-0.1.8.dist-info/RECORD
