Metadata-Version: 2.4
Name: vistopics
Version: 0.1.8
Summary: A package for video and image processing with captioning capabilities
Home-page: https://github.com/aysedeniz09/VisTopics
Author: Ayse D. Lokmanoglu & Dror Walter
Author-email: alokman@bu.edu
License: MIT
Classifier: Programming Language :: Python :: 3
Classifier: License :: OSI Approved :: MIT License
Classifier: Operating System :: OS Independent
Requires-Python: >=3.9
License-File: LICENSE
Requires-Dist: openai>=1.50.0
Requires-Dist: opencv-python<4.10,>=4.9.0
Requires-Dist: opencv-python-headless<4.10,>=4.9.0
Requires-Dist: pandas<2.2,>=2.0.3
Requires-Dist: requests>=2.28.0
Requires-Dist: yt-dlp>=2024.12.6
Requires-Dist: gradio>=3.36.0
Requires-Dist: aiofiles>=23.0
Requires-Dist: pydantic>=2.8
Requires-Dist: urllib3>=1.26
Requires-Dist: beautifulsoup4>=4.12
Provides-Extra: fastdup
Requires-Dist: fastdup>=2.15; extra == "fastdup"
Requires-Dist: numpy~=1.23.0; extra == "fastdup"
Dynamic: author
Dynamic: author-email
Dynamic: classifier
Dynamic: description
Dynamic: description-content-type
Dynamic: home-page
Dynamic: license
Dynamic: license-file
Dynamic: provides-extra
Dynamic: requires-dist
Dynamic: requires-python
Dynamic: summary
